README.md
setup.py
funnlp.egg-info/PKG-INFO
funnlp.egg-info/SOURCES.txt
funnlp.egg-info/dependency_links.txt
funnlp.egg-info/requires.txt
funnlp.egg-info/top_level.txt
nlp/__init__.py
nlp/augmentation/__init__.py
nlp/augmentation/eda.py
nlp/classfication/__init__.py
nlp/classfication/fasttext_classifier.py
nlp/classfication/svm_classifier.py
nlp/classfication/dl/__init__.py
nlp/classfication/dl/base_classifier.py
nlp/classfication/dl/bert_classifier.py
nlp/classfication/dl/cnn_classifier.py
nlp/classfication/dl/han_classifier.py
nlp/classfication/dl/rcnn_classifier.py
nlp/classfication/dl/rnn_attention_classifier.py
nlp/classfication/dl/rnn_classifier.py
nlp/embedding/__init__.py
nlp/embedding/fasttext_model.py
nlp/embedding/word2vec.py
nlp/layers/__init__.py
nlp/layers/attention.py
nlp/layers/decoder.py
nlp/layers/encoder.py
nlp/layers/layer_norm.py
nlp/layers/multi_head_attention.py
nlp/layers/position_encoding.py
nlp/ner/__init__.py
nlp/ner/bilstm_crf.py
nlp/nmt/__init__.py
nlp/nmt/transformer.py
nlp/nmt/seq2seq/__init__.py
nlp/nmt/seq2seq/preprocess.py
nlp/nmt/seq2seq/seq2seq.py
nlp/nmt/seq2seq/train.py
nlp/simililarity/__init__.py
nlp/simililarity/siamese_similarity.py
nlp/topic/__init__.py
nlp/topic/lda_topic.py
nlp/utils/__init__.py
nlp/utils/basic_log.py
nlp/utils/clean_text.py
nlp/utils/plot_model_history.py
nlp/utils/pre_process.py
nlp/utils/set_stopwords.py