Metadata-Version: 2.1
Name: funnlp
Version: 0.0.2
Summary: Easy-to-use and Extendible package of deep learning based nlp (Natural Language Processing) tools with tensorflow 2.x .
Home-page: https://github.com/msgi/nlp-journey.git
Author: msgi(慢时光)
Author-email: mayuan120226@sina.cn
License: Apache-2.0
Keywords: nlp,natural language processing,nlu,natural language understandingdeep learning,tensorflow,keras
Platform: UNKNOWN
Classifier: License :: OSI Approved :: Apache Software License
Classifier: Operating System :: OS Independent
Classifier: Intended Audience :: Developers
Classifier: Intended Audience :: Education
Classifier: Intended Audience :: Science/Research
Classifier: Programming Language :: Python :: 3.6
Classifier: Programming Language :: Python :: 3.7
Classifier: Topic :: Scientific/Engineering
Classifier: Topic :: Scientific/Engineering :: Artificial Intelligence
Classifier: Topic :: Software Development
Classifier: Topic :: Software Development :: Libraries
Classifier: Topic :: Software Development :: Libraries :: Python Modules
Requires-Python: >=3.6
Provides-Extra: cpu
Provides-Extra: gpu
